ping_game_theory_25/__init__.py
ping_game_theory_25/py.typed
ping_game_theory_25-0.1.3.dist-info/WHEEL
ping_game_theory_25-0.1.3.dist-info/entry_points.txt
ping_game_theory_25-0.1.3.dist-info/METADATA
ping_game_theory_25-0.1.3.dist-info/RECORD
