Metadata-Version: 2.3
Name: ping-game-theory-25
Version: 0.1.3
Summary: Driver Code for @ping/game-theory-25
Author: lalitm1004
Author-email: lalitm1004 <lalitm1004@gmail.com>
Requires-Dist: tqdm>=4.67.1
Requires-Python: >=3.9
